livescraper/__init__.py
livescraper/scraper.py
livescraper-1.5.2.dist-info/METADATA
livescraper-1.5.2.dist-info/WHEEL
livescraper-1.5.2.dist-info/top_level.txt
livescraper-1.5.2.dist-info/RECORD
