Metadata-Version: 2.2
Name: livescraper
Version: 1.5.2
Summary: Python bindings for the Livescraper API
Home-page: 
Author: livescraper
Author-email: livescraper@gmail.com
License: MIT
Keywords: livescraper webscraper extractor google api maps search json scrape parser reviews google play
Classifier: Programming Language :: Python :: 3
Classifier: License :: OSI Approved :: MIT License
Classifier: Operating System :: OS Independent
Classifier: Intended Audience :: Developers
Classifier: Topic :: Utilities
Classifier: Development Status :: 5 - Production/Stable
Requires-Python: >=3.6
Requires-Dist: requests
Dynamic: author
Dynamic: author-email
Dynamic: classifier
Dynamic: description
Dynamic: description-content-type
Dynamic: keywords
Dynamic: license
Dynamic: requires-dist
Dynamic: requires-python
Dynamic: summary
